{
    "Modules": {
        "...MASTER...": {},
        "std": {
            "Compiled Times": 2,
            "Compiled": "Yes"
        },
        "tb_get_ins": {
            "Compiled Times": 2,
            "Compiled": "Yes"
        },
        "ClkDiv": {
            "Compiled Times": 2,
            "Compiled": "Yes"
        },
        "ALEGen": {
            "Compiled Times": 2,
            "Compiled": "Yes"
        }
    },
    "reusePaths": {
        "amcQw_d": {
            "icPath": "csrc"
        },
        "reYIK_d": {
            "icPath": "csrc"
        },
        "GLQFB_d": {
            "icPath": "csrc"
        },
        "x91G7_d": {
            "icPath": "csrc"
        },
        "PJbHW_d": {
            "icPath": "csrc"
        }
    },
    "CompUnits": {},
    "ObjArchives": []
}